{"name":"服务器","slug":"服务器","count":2,"postlist":[{"title":"Tiny Tiny RSS再次搭建","uid":"ddd8f8b95edef17d3014e115ee93b047","slug":"ttrss-build-2","date":"2021-07-22T13:00:27.000Z","updated":"2022-08-18T03:13:04.135Z","comments":true,"path":"api/articles/ttrss-build-2.json","keywords":null,"cover":[],"text":"贫穷的Leon的腾讯云服务器快要到期了(发文章的时候已经到期了)，自用的TTRSS服务岌岌可危，这可咋整啊！！！所幸几周前已经把阿里云上的博客全部迁移到Gith...","link":"","photos":[],"count_time":{"symbolsCount":"4.1k","symbolsTime":"4 mins."},"categories":[{"name":"DIY","slug":"DIY","count":2,"path":"api/categories/DIY.json"}],"tags":[{"name":"DIY","slug":"DIY","count":5,"path":"api/tags/DIY.json"},{"name":"RSS","slug":"RSS","count":2,"path":"api/tags/RSS.json"},{"name":"服务器","slug":"服务器","count":2,"path":"api/tags/服务器.json"}],"author":{"name":"Leon","slug":"blog-author","avatar":"https://avatars.githubusercontent.com/u/17242727?s=60&v=4","link":"/","description":"这里是爱研究各种问题、立许多flag的Leon的网络日志","socials":{"github":"","twitter":"","stackoverflow":"","wechat":"","qq":"","weibo":"","zhihu":"","csdn":"","juejin":"","customs":{}}}},{"title":"自建RSS服务——Tiny Tiny RSS","uid":"e8150b3212a072c98bc817c2af2c678b","slug":"ttrss-build","date":"2020-04-23T13:16:19.000Z","updated":"2022-08-18T03:14:09.983Z","comments":true,"path":"api/articles/ttrss-build.json","keywords":null,"cover":[],"text":"这篇文章使用的是TTRSS老版本安装方式，新版的Docker安装请参考最新的文章Tiny Tiny RSS再次搭建。 很早之前就有了自建RSS服务的想法，但是F...","link":"","photos":[],"count_time":{"symbolsCount":"4k","symbolsTime":"4 mins."},"categories":[{"name":"DIY","slug":"DIY","count":2,"path":"api/categories/DIY.json"}],"tags":[{"name":"DIY","slug":"DIY","count":5,"path":"api/tags/DIY.json"},{"name":"RSS","slug":"RSS","count":2,"path":"api/tags/RSS.json"},{"name":"服务器","slug":"服务器","count":2,"path":"api/tags/服务器.json"}],"author":{"name":"Leon","slug":"blog-author","avatar":"https://avatars.githubusercontent.com/u/17242727?s=60&v=4","link":"/","description":"这里是爱研究各种问题、立许多flag的Leon的网络日志","socials":{"github":"","twitter":"","stackoverflow":"","wechat":"","qq":"","weibo":"","zhihu":"","csdn":"","juejin":"","customs":{}}}}]}